password_generator/__init__.py
password_generator/generator.py
secure_password_gen-0.1.0.dist-info/LICENSE
secure_password_gen-0.1.0.dist-info/METADATA
secure_password_gen-0.1.0.dist-info/WHEEL
secure_password_gen-0.1.0.dist-info/top_level.txt
secure_password_gen-0.1.0.dist-info/RECORD
